{
  "data": [
    {
      "trd": "1,65,25,844",
      "qty": "2,95,78,77,157",
      "val": "40,093.36",
      "utm": "16:00",
      "utmAs": "Jan 02, 2023",
      "mkt": "CM",
      "pre_val": "0.00",
      "valb": "400.93",
      "pre_valb": "0.00"
    },
    {
      "trd": "1,46,170",
      "qty": "2,40,621",
      "val": "24,064.13",
      "utm": "15:30",
      "utmAs": "Jan 02, 2023",
      "mkt": "FNOFUT",
      "pre_val": "0.00",
      "valb": "240.64",
      "pre_valb": "0.00"
    },
    {
      "trd": "4,44,79,148",
      "qty": "11,77,09,477",
      "val": "41,793.00",
      "utm": "15:30",
      "utmAs": "Jan 02, 2023",
      "mkt": "FNOOPT",
      "pre_val": "1,13,93,202.81",
      "valb": "417.93",
      "pre_valb": "1,13,932.03"
    },
    {
      "trd": "-",
      "qty": "-",
      "val": "-",
      "utm": "-",
      "utmAs": "",
      "mkt": "FNOIVX",
      "pre_val": "-",
      "valb": "-",
      "pre_valb": "-"
    },
    {
      "trd": "4,90,061",
      "qty": "5,59,131",
      "val": "39,825.09",
      "utm": "15:30",
      "utmAs": "Jan 02, 2023",
      "mkt": "FNOSTKFUT",
      "pre_val": "0.00",
      "valb": "398.25",
      "pre_valb": "0.00"
    },
    {
      "trd": "16,47,862",
      "qty": "20,18,840",
      "val": "2,791.36",
      "utm": "15:30",
      "utmAs": "Jan 02, 2023",
      "mkt": "FNOSTKOPT",
      "pre_val": "1,49,830.35",
      "valb": "27.91",
      "pre_valb": "1,498.30"
    },
    {
      "trd": "-",
      "qty": "-",
      "val": "-",
      "utm": "-",
      "utmAs": "",
      "mkt": "GIFUT",
      "pre_val": "-",
      "valb": "-",
      "pre_valb": "-"
    },
    {
      "trd": "-",
      "qty": "-",
      "val": "-",
      "utm": "-",
      "utmAs": "",
      "mkt": "GIOPT",
      "pre_val": "-",
      "valb": "-",
      "pre_valb": "-"
    },
    {
      "trd": "1,37,636",
      "qty": "29,58,762",
      "val": "24,759.46",
      "utm": "17:00",
      "utmAs": "Jan 02, 2023",
      "mkt": "FUTCUR",
      "pre_val": "0.00",
      "valb": "247.59",
      "pre_valb": "0.00"
    },
    {
      "trd": "1,75,928",
      "qty": "84,42,641",
      "val": "112.91",
      "utm": "17:00",
      "utmAs": "Jan 02, 2023",
      "mkt": "OPTCUR",
      "pre_val": "69,998.35",
      "valb": "1.13",
      "pre_valb": "699.98"
    },
    {
      "trd": "35",
      "qty": "9,906",
      "val": "197.09",
      "utm": "17:00",
      "utmAs": "Jan 02, 2023",
      "mkt": "IRF",
      "pre_val": "0.00",
      "valb": "1.97",
      "pre_valb": "0.00"
    },
    {
      "trd": "1",
      "qty": "1",
      "val": "0.06",
      "utm": "23:23",
      "utmAs": "Jan 02, 2023",
      "mkt": "COMFUT",
      "pre_val": "0.00",
      "valb": "0.00",
      "pre_valb": "0.00"
    }
  ],
  "time": "Jan 02, 2023 17:00"
}