{
  "data": [
    {
      "prevMkt": "OPTCUR",
      "prevQty": "1,99,15,017",
      "oi": "80,91,531"
    },
    {
      "prevMkt": "FUTCUR",
      "prevQty": "69,05,949",
      "oi": "85,14,084"
    },
    {
      "prevMkt": "CM",
      "prevQty": "2,40,30,93,385",
      "oi": ""
    },
    {
      "prevMkt": "FNOFUT",
      "prevQty": "3,34,257",
      "oi": "3,72,931"
    },
    {
      "prevMkt": "FNOIVX",
      "prevQty": "0",
      "oi": "0"
    },
    {
      "prevMkt": "FNOSTKFUT",
      "prevQty": "25,76,511",
      "oi": "30,87,765"
    },
    {
      "prevMkt": "FNOOPT",
      "prevQty": "12,01,03,515",
      "oi": "99,33,994"
    },
    {
      "prevMkt": "GIFUT",
      "prevQty": "",
      "oi": ""
    },
    {
      "prevMkt": "FNOSTKOPT",
      "prevQty": "46,45,794",
      "oi": "25,49,021"
    },
    {
      "prevMkt": "GIOPT",
      "prevQty": "",
      "oi": ""
    },
    {
      "prevMkt": "IRF",
      "prevQty": "1,568",
      "oi": "35,646"
    },
    {
      "prevMkt": "COMFUT",
      "prevQty": "2,79,810",
      "oi": "1,18,480"
    }
  ]
}