{
  "ICICI Bank ADR": {
    "chg_pct": "+2.05%",
    "volume": "7.44M",
    "month_chg_pct": "-2.16%"
  },
  "Infosys ADR": {
    "chg_pct": "+0.35%",
    "volume": "7.40M",
    "month_chg_pct": "-9.36%"
  },
  "Wipro ADR": {
    "chg_pct": "-0.21%",
    "volume": "1.72M",
    "month_chg_pct": "-5.28%"
  },
  "HDFC Bank ADR": {
    "chg_pct": "+1.10%",
    "volume": "1.47M",
    "month_chg_pct": "-7.02%"
  },
  "Azure Power Global": {
    "chg_pct": "+6.03%",
    "volume": "937.97K",
    "month_chg_pct": "-43.58%"
  },
  "Dr. Reddy\u2019s Labs ADR": {
    "chg_pct": "-0.35%",
    "volume": "326.61K",
    "month_chg_pct": "-2.42%"
  },
  "MakeMyTrip": {
    "chg_pct": "-0.20%",
    "volume": "292.05K",
    "month_chg_pct": "-8.90%"
  },
  "WNS Holdings": {
    "chg_pct": "+1.52%",
    "volume": "124.91K",
    "month_chg_pct": "5.67%"
  },
  "Sify": {
    "chg_pct": "+1.55%",
    "volume": "97.93K",
    "month_chg_pct": "-20.12%"
  },
  "Yatra Online": {
    "chg_pct": "-0.49%",
    "volume": "82.86K",
    "month_chg_pct": "-12.02%"
  },
  "Lytus Technologies Holdings Ptv": {
    "chg_pct": "-2.42%",
    "volume": "68.21K",
    "month_chg_pct": "-20.73%"
  },
  "Rediff.com India": {
    "chg_pct": "0.00%",
    "volume": "0",
    "month_chg_pct": "0.00%"
  },
  "Axis Bank ADR": {
    "chg_pct": "0.00%",
    "volume": "0",
    "month_chg_pct": "0.00%"
  }
}