{
  "Infosys ADR": {
    "chg_pct": "-0.93%",
    "volume": "11.72M",
    "month_chg_pct": "3.46%"
  },
  "ICICI Bank ADR": {
    "chg_pct": "-0.58%",
    "volume": "3.78M",
    "month_chg_pct": "-5.03%"
  },
  "Wipro ADR": {
    "chg_pct": "+0.20%",
    "volume": "1.38M",
    "month_chg_pct": "2.30%"
  },
  "HDFC Bank ADR": {
    "chg_pct": "+0.47%",
    "volume": "881.78K",
    "month_chg_pct": "0.67%"
  },
  "MakeMyTrip": {
    "chg_pct": "-3.39%",
    "volume": "376.45K",
    "month_chg_pct": "-7.74%"
  },
  "Azure Power Global": {
    "chg_pct": "-5.13%",
    "volume": "211.27K",
    "month_chg_pct": "-16.75%"
  },
  "WNS Holdings": {
    "chg_pct": "-0.17%",
    "volume": "197.11K",
    "month_chg_pct": "2.79%"
  },
  "Lytus Technologies Holdings Ptv": {
    "chg_pct": "-7.95%",
    "volume": "126.58K",
    "month_chg_pct": "3.98%"
  },
  "Dr. Reddy\u2019s Labs ADR": {
    "chg_pct": "+0.99%",
    "volume": "95.20K",
    "month_chg_pct": "2.44%"
  },
  "Yatra Online": {
    "chg_pct": "+2.74%",
    "volume": "91.12K",
    "month_chg_pct": "-12.45%"
  },
  "Sify": {
    "chg_pct": "-4.62%",
    "volume": "83.14K",
    "month_chg_pct": "-26.34%"
  },
  "Rediff.com India": {
    "chg_pct": "+0.00%",
    "volume": "4.00K",
    "month_chg_pct": "100.00%"
  },
  "Axis Bank ADR": {
    "chg_pct": "0.00%",
    "volume": "0",
    "month_chg_pct": "0.00%"
  }
}